dependency_inspector/__init__.py
dependency_inspector/main.py
dependency_inspector/model.py
dependency_inspector/provider.py
dependency_inspector/registry.py
dependency_inspector-0.2.2.dist-info/LICENSE
dependency_inspector-0.2.2.dist-info/METADATA
dependency_inspector-0.2.2.dist-info/WHEEL
dependency_inspector-0.2.2.dist-info/entry_points.txt
dependency_inspector-0.2.2.dist-info/RECORD
