Metadata-Version: 2.1
Name: dependency_inspector
Version: 0.2.2
Summary: A common dependencies checker/resolver.
Home-page: https://github.com/MrLYC/DependencyInspector
Author: MrLYC
Author-email: fimyikong@gmail.com
Requires-Python: >=3.8,<4.0
Classifier: Programming Language :: Python :: 3
Classifier: Programming Language :: Python :: 3.8
Classifier: Programming Language :: Python :: 3.9
Classifier: Programming Language :: Python :: 3.10
Classifier: Programming Language :: Python :: 3.11
Requires-Dist: click (>=8.1.7,<9.0.0)
Requires-Dist: packaging (>=23.1,<24.0)
Requires-Dist: pydantic (>=2.3.0,<3.0.0)
Requires-Dist: pyyaml (>=6.0.1,<7.0.0)
Requires-Dist: resolvelib (>=1.0.1,<2.0.0)
Project-URL: Documentation, https://mrlyc.github.io/DependencyInspector/
Project-URL: Repository, https://github.com/MrLYC/DependencyInspector
